aio_aerospike_python/__init__.py
aio_aerospike_python/aio_aerospike_client.py
aio_aerospike_python/aio_aerospike_query.py
aio_aerospike_python/aio_aerospike_scan.py
aio_aerospike_python/exception.py
aio_aerospike_python-0.0.5.dist-info/LICENSE.txt
aio_aerospike_python-0.0.5.dist-info/METADATA
aio_aerospike_python-0.0.5.dist-info/WHEEL
aio_aerospike_python-0.0.5.dist-info/top_level.txt
aio_aerospike_python-0.0.5.dist-info/RECORD
