Metadata-Version: 2.1
Name: aio-aerospike-python
Version: 0.0.5
Summary: Asyncio wrapper of the Aerospike python client
Author-email: David Levy <davidvoler@gmail.com>, David Levy <david@datacontinuo.com>
Project-URL: Homepage, https://github.com/datacontinuo/aio_aerospike_python
Project-URL: Bug Tracker, https://github.com/datacontinuo/aio_aerospike_python/issues
Classifier: Programming Language :: Python :: 3
Classifier: License :: OSI Approved :: Apache Software License
Classifier: Operating System :: OS Independent
Requires-Python: >=3.7
License-File: LICENSE.txt
